vsf/__init__.py
vsf/constructors.py
vsf/core/__init__.py
vsf/core/base_vsf.py
vsf/core/neural_vsf.py
vsf/core/point_vsf.py
vsf/core/vsf_factory.py
vsf/dataset/__init__.py
vsf/dataset/base_dataset.py
vsf/dataset/constructors.py
vsf/dataset/file_loader_dataset.py
vsf/dataset/multi_modal_dataset.py
vsf/estimator/__init__.py
vsf/estimator/base_material_estimator.py
vsf/estimator/neural_vsf_estimator.py
vsf/estimator/point_vsf_estimator.py
vsf/estimator/point_vsf_meta_learning.py
vsf/estimator/quad_prog_optimizer.py
vsf/estimator/recursive_optimizer.py
vsf/prior/conditional_distribution.py
vsf/prior/constructors.py
vsf/prior/distribution.py
vsf/prior/prior_factory.py
vsf/prior/structured_prior_factory.py
vsf/sensor/__init__.py
vsf/sensor/base_calibrator.py
vsf/sensor/base_sensor.py
vsf/sensor/constructors.py
vsf/sensor/force_torque_sensor.py
vsf/sensor/joint_torque_sensor.py
vsf/sensor/punyo_dense_force_sensor.py
vsf/sensor/punyo_pressure_sensor.py
vsf/sim/__init__.py
vsf/sim/constructors.py
vsf/sim/klampt_world_wrapper.py
vsf/sim/metrics.py
vsf/sim/neural_vsf_body.py
vsf/sim/point_vsf_body.py
vsf/sim/quasistatic_sim.py
vsf/sim/rigid_body_integrator.py
vsf/sim/sim_state_cache.py
vsf/utils/__init__.py
vsf/utils/config_utils.py
vsf/utils/data_utils.py
vsf/utils/klampt_utils.py
vsf/utils/perf.py
vsf/utils/plot_utils.py
vsf/utils/vtk_utils.py
vsf/visualize/common.py
vsf/visualize/klampt_visualization.py
vsf/visualize/o3d_visualization.py
vsf/visualize/pyvista_visualization.py
openvsf-0.0.1.dist-info/METADATA
openvsf-0.0.1.dist-info/WHEEL
openvsf-0.0.1.dist-info/top_level.txt
openvsf-0.0.1.dist-info/RECORD
