Metadata-Version: 2.4
Name: openvsf
Version: 0.0.1
Summary: Open volumetric stiffness field
Author-email: Shaoxiong Yao <sy@abc.edu>, Jiaheng Han <jh@abc.edu>, Kris Hauser <kh@abc.edu>
License: MIT
Keywords: tactile model,simulation,estimation
Classifier: Programming Language :: Python :: 3
Classifier: Development Status :: 4 - Beta
Classifier: Natural Language :: English
Classifier: Operating System :: OS Independent
Classifier: Topic :: Scientific/Engineering
Requires-Dist: numpy
Requires-Dist: scipy
Requires-Dist: torch
Requires-Dist: open3d
Requires-Dist: meshio
Requires-Dist: trimesh[easy]
Requires-Dist: klampt>=0.10.0
Requires-Dist: mesh2sdf
Requires-Dist: cvxpy
Requires-Dist: dacite
Requires-Dist: opencv-python
Requires-Dist: PyOpenGL
Requires-Dist: PyQt5
